guardian_vaultwarden/__about__.py
guardian_vaultwarden/__init__.py
guardian_vaultwarden/client.py
guardian_vaultwarden/crypto.py
guardian_vaultwarden-0.1.1.dist-info/METADATA
guardian_vaultwarden-0.1.1.dist-info/WHEEL
guardian_vaultwarden-0.1.1.dist-info/licenses/LICENSE
guardian_vaultwarden-0.1.1.dist-info/RECORD
