Metadata-Version: 2.4
Name: guardian_vaultwarden
Version: 0.1.1
Summary: Vaultwarden ciphers API client
Project-URL: Homepage, https://github.com/Pluvie/guardian
Project-URL: Documentation, https://github.com/Pluvie/guardian
Author-email: Francesco Ballardin <francesco.ballardin@gmail.com>
License-Expression: GPL-3.0-only
License-File: LICENSE
Classifier: Development Status :: 5 - Production/Stable
Classifier: Intended Audience :: Information Technology
Classifier: Operating System :: POSIX :: Linux
Classifier: Programming Language :: Python :: 3.12
Classifier: Topic :: Security
Requires-Dist: hkdf
Requires-Dist: pycryptodome
Requires-Dist: requests
